samanageautomation/__init__.py
samanageautomation/update_incidents.py
samanageautomation-0.0.2.dist-info/LICENSE
samanageautomation-0.0.2.dist-info/METADATA
samanageautomation-0.0.2.dist-info/WHEEL
samanageautomation-0.0.2.dist-info/top_level.txt
samanageautomation-0.0.2.dist-info/RECORD
