Metadata-Version: 2.1
Name: samanageautomation
Version: 0.0.2
Summary: A class for managing a database of Samanage trouble ticket data
Home-page: https://github.com/portofsandiego/samanage-automation
Author: Bryan D. Hayes
Author-email: bhayes@portofsandiego.org
License: UNKNOWN
Platform: UNKNOWN
Classifier: Development Status :: 3 - Alpha
Classifier: Programming Language :: Python :: 3
Classifier: License :: OSI Approved :: MIT License
Classifier: Operating System :: OS Independent
Requires-Dist: requests
Requires-Dist: pandas
Requires-Dist: pyodbc
